bootstrap.py
buildout.cfg
setup.py
iw/__init__.py
iw.recipe.template.egg-info/PKG-INFO
iw.recipe.template.egg-info/SOURCES.txt
iw.recipe.template.egg-info/dependency_links.txt
iw.recipe.template.egg-info/entry_points.txt
iw.recipe.template.egg-info/namespace_packages.txt
iw.recipe.template.egg-info/not-zip-safe
iw.recipe.template.egg-info/requires.txt
iw.recipe.template.egg-info/top_level.txt
iw/recipe/__init__.py
iw/recipe/template/README.txt
iw/recipe/template/__init__.py
iw/recipe/template/proxy_vhost_tmpl
iw/recipe/template/docs/README.txt
iw/recipe/template/docs/vhosts.txt
iw/recipe/template/doctests/README.txt
iw/recipe/template/tests/__init__.py
iw/recipe/template/tests/test_templatedocs.py
