Metadata-Version: 1.0
Name: iw.recipe.template
Version: 0.1
Summary: ZC buildout recipe to build template based file
Home-page: UNKNOWN
Author: Ingeniweb
Author-email: support@ingeniweb.com
License: GPL
Platform: UNKNOWN
Classifier: Programming Language :: Python
Classifier: Topic :: Software Development :: Libraries :: Python Modules
